Workbook

Sheet Summary
A1: Guardian deployment test: Cortex platform tenant
A3: Tenant
A4: Tenant type (for example Cortex Cloud)
A5: Guardian content version
A6: Model provider and deployment
A7: Tester(s)
A8: Started
A9: Finished
A11: How to use this file
A12: 1. Make a copy of this file for each tenant.
A13: 2. Work through the Tests tab top to bottom.
A14: 3. Set each test's Status (it starts as "Not run").
... A19: Progress
A20: Part | B20: Tests | C20: Not run | D20: Pass | E20: Fail | F20: Blocked | G20: Skipped | H20: N/A | I20: Done | J20: % done
A21: 0 Before the session | B21: =COUNTIF(Tests!$B$2:$B$200,"0 Before") | C21: =COUNTIFS(Tests!$B$2:$B$200,"0 Before",Tests!$I$2:$I$200,"Not run") | D21: =COUNTIFS(Tests!$B$2:$B$200,"0 Before",Tests!$I$2:$I$200,"Pass") | E21: =COUNTIFS(Tests!$B$2:$B$200,"0 Before",Tests!$I$2:$I$200,"Fail") | F21: =COUNTIFS(Tests!$B$2:$B$200,"0 Before",Tests!$I$2:$I$200,"Blocked") | G21: =COUNTIFS(Tests!$B$2:$B$200,"0 Before",Tests!$I$2:$I$200,"Skipped") | H21: =COUNTIFS(Tests!$B$2:$B$200,"0 Before",Tests!$I$2:$I$200,"N/A") | I21: =B21-C21 | J21: =IF(B21=0,0,I21/B21)
A22: Part 1: without a model | B22: =COUNTIF(Tests!$B$2:$B$200,"1 No model") | C22: =COUNTIFS(Tests!$B$2:$B$200,"1 No model",Tests!$I$2:$I$200,"Not run") | D22: =COUNTIFS(Tests!$B$2:$B$200,"1 No model",Tests!$I$2:$I$200,"Pass") | E22: =COUNTIFS(Tests!$B$2:$B$200,"1 No model",Tests!$I$2:$I$200,"Fail") | F22: =COUNTIFS(Tests!$B$2:$B$200,"1 No model",Tests!$I$2:$I$200,"Blocked") | G22: =COUNTIFS(Tests!$B$2:$B$200,"1 No model",Tests!$I$2:$I$200,"Skipped") | H22: =COUNTIFS(Tests!$B$2:$B$200,"1 No model",Tests!$I$2:$I$200,"N/A") | I22: =B22-C22 | J22: =IF(B22=0,0,I22/B22)
A23: Part 2: connect the model | B23: =COUNTIF(Tests!$B$2:$B$200,"2 Model") | C23: =COUNTIFS(Tests!$B$2:$B$200,"2 Model",Tests!$I$2:$I$200,"Not run") | D23: =COUNTIFS(Tests!$B$2:$B$200,"2 Model",Tests!$I$2:$I$200,"Pass") | E23: =COUNTIFS(Tests!$B$2:$B$200,"2 Model",Tests!$I$2:$I$200,"Fail") | F23: =COUNTIFS(Tests!$B$2:$B$200,"2 Model",Tests!$I$2:$I$200,"Blocked") | G23: =COUNTIFS(Tests!$B$2:$B$200,"2 Model",Tests!$I$2:$I$200,"Skipped") | H23: =COUNTIFS(Tests!$B$2:$B$200,"2 Model",Tests!$I$2:$I$200,"N/A") | I23: =B23-C23 | J23: =IF(B23=0,0,I23/B23)
A24: Part 3: with the model | B24: =COUNTIF(Tests!$B$2:$B$200,"3 With model") | C24: =COUNTIFS(Tests!$B$2:$B$200,"3 With model",Tests!$I$2:$I$200,"Not run") | D24: =COUNTIFS(Tests!$B$2:$B$200,"3 With model",Tests!$I$2:$I$200,"Pass") | E24: =COUNTIFS(Tests!$B$2:$B$200,"3 With model",Tests!$I$2:$I$200,"Fail") | F24: =COUNTIFS(Tests!$B$2:$B$200,"3 With model",Tests!$I$2:$I$200,"Blocked") | G24: =COUNTIFS(Tests!$B$2:$B$200,"3 With model",Tests!$I$2:$I$200,"Skipped") | H24: =COUNTIFS(Tests!$B$2:$B$200,"3 With model",Tests!$I$2:$I$200,"N/A") | I24: =B24-C24 | J24: =IF(B24=0,0,I24/B24)
A25: Total | B25: =COUNTA(Tests!$B$2:$B$200) | C25: =COUNTIF(Tests!$I$2:$I$200,"Not run") | D25: =COUNTIF(Tests!$I$2:$I$200,"Pass") | E25: =COUNTIF(Tests!$I$2:$I$200,"Fail") | F25: =COUNTIF(Tests!$I$2:$I$200,"Blocked") | G25: =COUNTIF(Tests!$I$2:$I$200,"Skipped") | H25: =COUNTIF(Tests!$I$2:$I$200,"N/A") | I25: =B25-C25 | J25: =IF(B25=0,0,I25/B25)

Sheet Tests
A1: ID | B1: Part | C1: Section | D1: Test | E1: Steps | F1: Expected | G1: Billed | H1: Optional | I1: Status | J1: Evidence | K1: Notes | L1: Date | M1: By
A2: B1 | B2: 0 Before | C2: 0 Before the session | D2: Part 1: content installed | E2: The Guardian content is installed. On a tenant without layouts, some layouts, issue types or dashboards may not have installed: test P1 records what is there. | F2: Ready | I2: Not run
A3: B2 | B3: 0 Before | C3: 0 Before the session | D3: Part 1: account permissions | E3: You have an account that can create integration instances, run commands in a War Room, read Lists and set an issue's playbook. | F3: Ready | I3: Not run
A4: B3 | B4: 0 Before | C4: 0 Before the session | D4: Part 1: Core REST API key | E4: A Standard-level API key and its key ID, for the Core REST API instance (P4). docs/cortex-platform/README.md, "Prerequisites", says how to create one. | F4: Ready | I4: Not run
A5: B4 | B5: 0 Before | C5: 0 Before the session | D5: Part 1: test issues chosen | E5: Test issues chosen: one workbench issue; two or three investigation issues of different kinds (one you believe is a false positive, one real finding, one with entities such as an IP address, host, user or hash); and one spare issue that may be closed: a test issue, not a real alert (S3 targets it and O2 closes it). Guardian adds notes and fields to these issues. It cannot close them or change anything else without an approval. | F5: Ready | I5: Not run
A6: B5 | B6: 0 Before | C6: 0 Before the session | D6: Part 2: model account ready | E6: The model provider account is ready, following docs/MODEL_SETUP.md. For Microsoft Foundry: an app registration (it appears under Enterprise applications) with either a client secret or the public certificate uploaded (then the combined PEM file, private key and certificate, at hand), a role on the Foundry resource, and a custom subdomain on the resource. | F6: Ready | I6: Not run
A7: B6 | B7: 0 Before | C7: 0 Before the session | D7: Part 2: network access | E7: The tenant can reach the model over HTTPS (443): the Foundry resource endpoint and, for Entra ID, login.microsoftonline.com. If the Foundry resource limits networks (Selected networks), the tenant's outbound IP addresses are allowed. | F7: Ready | I7: Not run
A8: B7 | B8: 0 Before | C8: 0 Before the session | D8: Part 2: token quota | E8: The deployment has enough tokens-per-minute quota. A Guardian turn is tens of thousands of tokens, and a small quota answers HTTP 429. | F8: Ready | I8: Not run
A9: P1 | B9: 1 No model | C9: 1 Preflight | D9: Content present | E9: In the scripts, playbooks, lists and integrations pages, search for Guardian. Count what is installed. | F9: 3 integrations (Guardian Foundry, Guardian Vertex, Guardian Cohere), 77 automations, 21 playbooks, 25 lists, 15 issue fields, 10 indicator fields, 2 issue types, 1 indicator type. On this profile, record any layouts, issue types or dashboards that are missing. | I9: Not run
A10: P2 | B10: 1 No model | C10: 1 Preflight | D10: Content editable | E10: Open one Guardian automation and one Guardian list. | F10: If the content was installed item by item (not as a pack), both can be edited. A pack install makes them read-only. Record which you have. | I10: Not run
A11: P3 | B11: 1 No model | C11: 1 Preflight | D11: Playbooks adopted | E11: Open the playbooks GuardianInvestigateIssue and GuardianHousekeeping. | F11: No "playbook is not adopted" message. If there is one, adopt the playbooks (docs/cortex-platform/README.md, "Adopt the playbooks"). | I11: Not run
A12: P4 | B12: 1 No model | C12: 1 Preflight | D12: Core REST API instance | E12: Create a Core REST API instance (docs/cortex-platform/README.md, "Prerequisites"): the Core Server URL from Copy API URL, the Standard key ID and key. Press Test, then run !core-api-post uri=/settings/integration/search body={"size":1} | F12: Success, then a JSON result with no error. This is not a model. Guardian uses it to write results onto the issue, to read the provider instances (!guardian-model, the model probe), and for housekeeping, case capture and simulated issues. Without it, those fail and the run summary on the issue stays empty. | I12: Not run
A13: P5 | B13: 1 No model | C13: 1 Preflight | D13: Bootstrap | E13: !GuardianBootstrap | F13: It creates the runtime lists: guardian_kill_switch, guardian_audit, guardian_cost_ledger, guardian_memory, guardian_approvals_ledger, guardian_jobs_registry, guardian_seed_version, guardian_skills_crud_index, guardian_model_calibration, guardian_model_profile. Run it before every other test: nothing else creates these lists. Running it again is safe. | I13: Not run
... A26: L8 | B26: 1 No model | C26: 2 Control lists | D26: Skills and knowledge base | E26: !getList listName=guardian_skills_index, then !getList listName=guardian_kb_soc_investigation | F26: Ten skills: cortex_issue_reference, cortex_xql, cortex_detection_investigation, cortex_posture_misconfiguration, cortex_identity_risk, cortex_vulnerability_triage, cortex_attack_path, cortex_case_investigation, build_cortex_playbook and cortex_triage. Then 43 knowledge-base entries, each with an ATT&CK technique. | I26: Not run
A27: L9 | B27: 1 No model | C27: 2 Control lists | D27: Model catalogue | E27: !getList listName=guardian_model_catalog. The list is large (about 85 KB): check only that it opens as plain JSON, then search the War Room entry for the model you will use in Part 2 (for example gpt-5-mini). | F27: Plain JSON with "checked":"2026-10-09" and 146 models. Record whether your model is listed and its probe value: skip (a closed frontier model: its documented limits are used without a probe, M14) or confirm (an open-weight model: M7 confirms the window it is served with). A model that is not listed is sized by M7. | H27: Yes | I27: Not run
A28: H1 | B28: 1 No model | C28: 3 Tools and costs | D28: Tool catalogue | E28: !guardian-tools | F28: The tools the model will be offered: the allowlist, less the denylist, less commands this tenant does not have, trimmed to the token budget. Record which platform commands appear, and the Dropped by token budget row. This tenant may not have every module, so some of core-get-issues, core-get-cases, core-get-endpoints, core-list-risky-hosts, core-list-risky-users and xdr-xql-generic-query can be missing. A missing tool narrows what the agent can check. M8 repeats this after the model is sized. | I28: Not run
A29: H2 | B29: 1 No model | C29: 3 Tools and costs | D29: Cost report (zero) | E29: !guardian-cost | F29: "No cost has been recorded yet": no model call has been made. | I29: Not run
A30: S1 | B30: 1 No model | C30: 4 Safeguards | D30: Allowed skill read | E30: !GuardianToolBridge tool_name=GuardianSkillRead tool_args={"name":"cortex_triage"} | F30: status=ok and the skill text. An allowed read runs. | I30: Not run
A31: S2 | B31: 1 No model | C31: 4 Safeguards | D31: Allowed issue read | E31: !GuardianToolBridge tool_name=getIncidents tool_args={"id":"<workbench issue id>"} | F31: status=ok and the issue data. | I31: Not run
A32: S3 | B32: 1 No model | C32: 4 Safeguards | D32: Destructive action held | E32: !GuardianToolBridge tool_name=closeInvestigation tool_args={"id":"<spare issue id>"}, then !guardian-deny approval_id=<ID> reason="safeguard test" with the id it printed | F32: First "Action requires approval", with an approval id and risk tier destructive. Nothing is closed. Then "DENIED". A command that changes something never runs without a person. The spare issue is the target so that a mistaken approval closes nothing that matters. | I32: Not run
A33: S4 | B33: 1 No model | C33: 4 Safeguards | D33: Denylisted command denied | E33: !GuardianToolBridge tool_name=core-api-get tool_args={"uri":"/health"} | F33: status=denied (on the denylist). | I33: Not run
A34: S5 | B34: 1 No model | C34: 4 Safeguards | D34: Unknown command denied | E34: !GuardianToolBridge tool_name=NotARealCommand tool_args={} | F34: status=denied: neither allowed nor in the policy, so refused by default. | I34: Not run
A35: S6 | B35: 1 No model | C35: 4 Safeguards | D35: Tool ledger rows | E35: !GuardianLayoutToolLedger | F35: One row for each of S1 to S5, with the status each one got. | I35: Not run
A36: A1 | B36: 1 No model | C36: 5 Human approval | D36: Hold an action | E36: Hold: !GuardianToolBridge tool_name=GuardianContainmentSimulate tool_args={"endpoint_id":"lab-host-01","reason":"gate-test"} | F36: "Action requires approval", with an approval id and risk tier soft. Nothing runs. | I36: Not run
A37: A2 | B37: 1 No model | C37: 5 Human approval | D37: Pending approval listed | E37: !GuardianWidgetApprovalsQueue, then !GuardianLayoutRecommendedActions | F37: Both list the pending approval with the same id. | I37: Not run
A38: A3 | B38: 1 No model | C38: 5 Human approval | D38: Approve the action | E38: !guardian-approve approval_id=<ID> | F38: "APPROVED". | I38: Not run
A39: A4 | B39: 1 No model | C39: 5 Human approval | D39: Execute approved action | E39: Execute: the A1 command with approval_id=<ID> added at the end. | F39: status=ok. The action runs once. Do not re-run the plain A1 command: that parks a new approval. | I39: Not run
... A55: O2 | B55: 1 No model | C55: 8 Upkeep without Jobs | D55: Housekeeping playbook | E55: On the spare issue: !setPlaybook name=GuardianHousekeeping. When it finishes, run !GuardianPlaybookMonitor incident_id=<spare issue id> in the workbench issue. | F55: The playbook completes, and its last task closes the spare issue. The monitor reports the run as successful, with no failed tasks. This is how a Job would run it. | I55: Not run
A56: O3 | B56: 1 No model | C56: 8 Upkeep without Jobs | D56: Case capture | E56: Needs custom issue fields: N/A if P10 found them REJECTED or DROPPED. !GuardianCaseCapture | F56: It runs without error, and nothing is captured yet: no closed issue has a Guardian verdict. U2 repeats it after the runs. | H56: Yes | I56: Not run
A57: O4 | B57: 1 No model | C57: 8 Upkeep without Jobs | D57: Evaluation harvest | E57: Needs custom issue fields: N/A if P10 found them REJECTED or DROPPED. !GuardianEvalHarvest | F57: It runs without error, and no evaluation case is added yet. U3 repeats it. | H57: Yes | I57: Not run
A58: O5 | B58: 1 No model | C58: 8 Upkeep without Jobs | D58: Widget commands | E58: !GuardianWidgetCost, !GuardianWidgetToolLedger, !GuardianWidgetLoopHealth, !GuardianWidgetApprovalsQueue, !GuardianWidgetEventFeed | F58: Each returns a table, mostly empty for now. The approvals queue shows A9's hold. These stand in for the dashboard. | I58: Not run
A59: X1 | B59: 1 No model | C59: 9 Optional tests without a model | D59: Simulated issues | E59: Simulated issues (uses the Core REST API instance from P4): !GuardianSimulateIncidents scenario=phishing count=1. Other scenarios: brute_force, malware_beacon, benign_fp, generic. | F59: A new issue tagged as simulated. Record whether the issue was created at all on this tenant. If it was, you can investigate it in Part 3 instead of a real issue. | H59: Yes | I59: Not run
A60: X2 | B60: 1 No model | C60: 9 Optional tests without a model | D60: Pre-approved bypass mode | E60: Needs custom issue fields: N/A if P10 found them REJECTED or DROPPED. Pre-approved actions: on a test issue, set the field guardianapprovalmode to bypass. Then hold as in A1 on that issue. | F60: GuardianContainmentSimulate runs without a person and is audited auto_approved=true. Destructive and credential-tier actions still wait for a person. This needs the field to be settable on that issue's type: the Guardian fields are associated only with the type Guardian Agent Run (see I3). Set it back to manual afterwards. | H60: Yes | I60: Not run
A61: X3 | B61: 1 No model | C61: 9 Optional tests without a model | D61: Dashboard import | E61: Needs custom issue fields: N/A if P10 found them REJECTED or DROPPED. Dashboard: if the tenant can import dashboards, import the Guardian Performance dashboard. An item-by-item install cannot upload it, so import it by hand from the pack's dashboard file. | F61: Record whether the import works. It fills in once Part 3 has runs, if I3 finds the fields written. | H61: Yes | I61: Not run
A62: END1 | B62: 1 No model | C62: 8 Upkeep without Jobs | D62: End of Part 1 checkpoint | E62: Check that every required test in sections 1 to 8 has passed, then run !guardian-cost. | F62: Sections 1 to 8 pass, and !guardian-cost shows no cost: nothing has called a model. Fix any failure before Part 2 (see the Troubleshooting tab). | I62: Not run
A63: M1 | B63: 2 Model | C63: 10 Model provider | D63: Foundry instance saved | E63: Create a Guardian Foundry instance with the values from docs/MODEL_SETUP.md. In Model, choose your model (for example gpt-5-mini); choose Custom (use the deployment name below) only when your deployment has another name, and then fill in Deployment name. For a certificate, set Authentication to entra-client-certificate, fill in Tenant ID and Client ID, paste the whole PEM file (private key and certificate) into Certificate and private key, PEM, leave the thumbprint empty, and fill in the passphrase only if the key is encrypted. For a client secret, set Authentication to entra-client-credentials and fill in Tenant ID, Client ID and Client secret. Save. | F63: The instance saves. Record which Authentication you used. | I63: Not run
A64: M2 | B64: 2 Model | C64: 10 Model provider | D64: PEM field kept after save | E64: Certificate only (N/A with a client secret). Close the instance and open it again. | F64: The PEM field still holds a value (shown masked). This field type has not yet been tried in a console, so record the result. If the value is lost on save, switch to entra-client-credentials (client secret) so the session can continue, and report it. | I64: Not run
A65: M3 | B65: 2 Model | C65: 10 Model provider | D65: Instance Test | E65: Press Test. | F65: Success. If the error mentions the cryptography library or the Docker image, the tenant has not pulled the demisto/crypto image this integration now runs on. | I65: Not run
A66: M4 | B66: 2 Model | C66: 10 Model provider | D66: One active provider | E66: Disable every other Guardian provider instance, then run !guardian-model. | F66: One active instance: your Foundry instance, with the model chosen in its Model dropdown (or the Deployment name when Model is Custom), and the numbers a run started now would use, each with its source. For a model in the catalogue the model size comes from the catalogue (gpt-5-mini: large), and the limits follow its input budget. Before any profile is saved, a model in the catalogue that needs no probe already shows its documented input budget, marked as saved by the run's first task (gpt-5-mini on Foundry: 173400, documented, catalogue 2026-10-09), and a line saying no profile is saved yet and that !GuardianModelProfileCheck saves it now (M14). An open-weight model in the catalogue, or a model that is not in it, shows the guardian_settings budget (28258) and says how to size it (M7). Compare with P8. | I66: Not run
A67: M14 | B67: 2 Model | C67: 10 Model provider | D67: Documented profile saved | E67: !GuardianModelProfileCheck, then !guardian-model | F67: For a model in the model catalogue that needs no probe, or that has a published cloud provider cap: the output says the model is documented, with its context window and usable input limit, and that a documented profile was written with its input budget. For gpt-5-mini on Foundry: context window 400,000, usable input limit 272,000 tokens, input budget 173,400. The list guardian_model_profile is created if it was missing. !guardian-model then shows the same input budget with the source documented and the catalogue date. Running !GuardianModelProfileCheck again keeps the same budget. An open-weight model in the catalogue: no profile is written, and the output says to confirm the served window with !guardian-probe-model (M7). A model that is not in the catalogue: no profile is written; M7 sizes it. | I67: Not run
A68: M15 | B68: 2 Model | C68: 10 Model provider | D68: Model size | E68: Run !guardian-model. Only for a model that is not in the model catalogue: open the list guardian_settings and set "model_tier" to small (under 13B parameters), medium (13B to 40B) or large (over 40B, or a hosted frontier model), then run !guardian-model again. To force a size for a model that is in the catalogue, open the list guardian_model_profile (it exists after M14, or after M7) and set "overrides" to {"model_tier": "<size>"}, keeping the rest of the list as it is. | F68: For a model in the catalogue, Model size comes from the catalogue (gpt-5-mini: large), not from guardian_settings, and the limits follow the input budget. For gpt-5-mini at 173,400: tool list budget 43,350 (every allowlisted tool fits), each tool result up to about 138 KB, incident details up to 34,680 characters, and history trimmed only near the budget. If guardian_settings holds an explicit model_tier, the output says in one line that it is not used for this model. A model that is not in the catalogue takes the size set in guardian_settings (small when it is "auto"). The instance's own Model size field is display-only: "auto" or empty is fine, and a different value only gives a one-line note. | I68: Not run
A69: M5 | B69: 2 Model | C69: 10 Model provider | D69: Plain chat | E69: !guardian-llm-chat user_message="Reply with the single word OK" | F69: OK, with the model name and token counts. | G69: Yes | I69: Not run
A70: M6 | B70: 2 Model | C70: 10 Model provider | D70: Tool call | E70: A tool call: !guardian-llm-chat messages=`[{"role":"user","content":"What is the reputation of 8.8.8.8?"}]` tools=`[{"type":"function","function":{"name":"ip_reputation","description":"Look up IP reputation","parameters":{"type":"object","properties":{"ip":{"type":"string"}},"required":["ip"]}}}]` tool_choice=auto | F70: The answer contains a tool call to ip_reputation with ip = 8.8.8.8. | G70: Yes | I70: Not run
A71: M7 | B71: 2 Model | C71: 10 Model provider | D71: Model sized by hand | E71: Required for an open-weight, self-hosted or unknown model. Optional for a model that M14 saved a documented profile for: it then only measures characters per token and checks tool support. Size the model by hand, which is the model-adaptation Job's work: !guardian-probe-model, then !GuardianModelProfileUpdate, then !guardian-model. A model that is in the model catalogue and needs no probe (a closed frontier model) gets no window search: the probe measures only characters per token and the capability checks. Add force=true to search it anyway. | F71: The probe reports the catalogue match: the documented context window and usable input limit. A closed frontier model: no window probe needed (documented), and !GuardianModelProfileUpdate saves the documented profile again, now with the measured characters per token, counted as at most 3.0, so the input budget does not change (173,400 for gpt-5-mini) and the source stays documented. An open-weight or self-hosted model: the probe searches up to the documented limit and gives a verdict: confirmed (the window is within 20% of the documented limit, which is then used), measured (more than 20% below it, with the evidence, for example "past N tokens the first response took X s") or quota (a rate limit stopped the search, so the window was not reached; a frontier model or a model on a cloud with a published cap keeps the documented limit, a self-hosted model is sized from the largest request that answered). A model that is not in the catalogue is searched up to 131072 tokens. guardian_model_profile is written; !guardian-model shows the new size and budgets with their source. Without this step, runs use the documented profile of a known model, or the conservative small defaults. | G71: Yes | I71: Not run
A72: M8 | B72: 2 Model | C72: 10 Model provider | D72: Profile and tools after sizing | E72: !GuardianModelProfileCheck, then !guardian-tools | F72: The values now come from the profile on file (documented, confirmed or measured; compare with P9), each worded for its source: a documented figure is never called measured or probed. For a known model with no profile, this task writes the documented one itself, but only for a model that needs no probe or has a cloud provider cap; a self-hosted open-weight model is reported with its documented figure and advice to confirm the served window with !guardian-probe-model then !GuardianModelProfileUpdate. Compare the Dropped by token budget row with H1: a larger model can be offered more tools. | I72: Not run
A73: M9 | B73: 2 Model | C73: 10 Model provider | D73: PEM without certificate | E73: On a second Foundry instance, press Test without enabling it: Paste only the private key, and leave the thumbprint empty. | F73: "The PEM has no certificate, so the thumbprint cannot be computed. Enter the certificate thumbprint ..." | H73: Yes | I73: Not run
A74: M10 | B74: 2 Model | C74: 10 Model provider | D74: Wrong certificate thumbprint | E74: On a second Foundry instance, press Test without enabling it: Same as M9, but enter a thumbprint of a different certificate. | F74: "Entra ID did not accept the certificate assertion. Check that the PUBLIC certificate is uploaded to the app registration ..." | H74: Yes | I74: Not run
A75: M11 | B75: 2 Model | C75: 10 Model provider | D75: Encrypted key, no passphrase | E75: On a second Foundry instance, press Test without enabling it: Use an encrypted private key with no passphrase. | F75: "The private key is encrypted: enter its passphrase." | H75: Yes | I75: Not run
A76: M12 | B76: 2 Model | C76: 10 Model provider | D76: Certificate without role | E76: On a second Foundry instance, press Test without enabling it: Use the right certificate on an app that has no role on the Foundry resource. | F76: HTTP 401 or 403 from Foundry. After a role is added, wait up to five minutes before testing again. | H76: Yes | I76: Not run
A77: M13 | B77: 2 Model | C77: 10 Model provider | D77: Other providers | E77: Repeat M1 to M8, M14 and M15 for Guardian Vertex or Guardian Cohere, with the Foundry instance disabled. Guardian Cohere needs an engine. | F77: The same results as M1 to M8, M14 and M15, with that provider and its model. | H77: Yes | I77: Not run
A78: I1 | B78: 3 With model | C78: 11 Investigating an issue | D78: Start an investigation | E78: In the first investigation issue's War Room: !DeleteContext key=Guardian, then !setPlaybook name=GuardianInvestigateIssue | F78: The playbook starts. On this platform the War Room shows the loop's start entry and its conclusion; in between, an "Incident was modified" entry about every 30 to 40 seconds shows the turn count and cost rising. Record whether per-turn narration entries also appear. A run usually takes 4 to 10 turns, a few minutes in all. Among the first entries, the Resolve model profile task shows the model size and input budget the run uses, each with its source (catalogue and documented for gpt-5-mini: large, 173400). If no profile was saved before, it writes the documented one now. For a large model the tool catalogue entry lists every allowlisted tool present on the tenant, with no truncation warning. | G78: Yes | I78: Not run
A79: I2 | B79: 3 With model | C79: 11 Investigating an issue | D79: Run conclusion | E79: Wait for the run to finish. | F79: The conclusion ends with a verdict block: verdict (Benign, Suspicious, Malicious or Inconclusive), confidence, ATT&CK techniques, summary. Above it, the agent's analysis: the evidence it found and why it chose the verdict. If the run was asked to finish a missing step (a case note or a memory entry), the analysis is still there, followed by the final reply. A case note (War Room Notes). A per-run cost line. On a tenant without custom issue fields (P10), the narration also says once: "Verdict recorded in the conclusion and guardian_audit; not saved to the issue fields". That is expected, and the run does not retry. | I79: Not run
A80: I3 | B80: 3 With model | C80: 11 Investigating an issue | D80: Issue fields written | E80: Needs custom issue fields: N/A if P10 found them REJECTED or DROPPED. Look at the issue's fields: verdict, confidence, ATT&CK techniques, blast radius, tick count, cost, model, tool calls. | F80: Record whether the fields were written. The Guardian fields are associated only with the issue type Guardian Agent Run, so on other issue types they may not show, or may not be stored. If they are missing, the verdict is still in the conclusion, the case note and !GuardianLayoutTrace. If your tenant lets you associate fields with issue types, associate the Guardian fields with the types you test and re-run on another issue. | H80: Yes | I80: Not run
A81: I4 | B81: 3 With model | C81: 11 Investigating an issue | D81: Trace and tool ledger | E81: !GuardianLayoutTrace, then !GuardianLayoutToolLedger | F81: The turn-by-turn trace (status done), and every tool the agent called with its status. Denied rows show the gate working: record which tools were denied. | I81: Not run
A82: I5 | B82: 3 With model | C82: 11 Investigating an issue | D82: Other investigation issues | E82: Repeat I1 to I4 on the other investigation issues, one at a time. | F82: A sensible verdict for each. The false positive should not come out Malicious. | G82: Yes | I82: Not run
A83: I6 | B83: 3 With model | C83: 11 Investigating an issue | D83: Answer the agent | E83: While a run is going, answer any question the agent posts with !guardian-chat message="<your answer>". | F83: The next turn uses your answer. | G83: Yes | I83: Not run
A84: I7 | B84: 3 With model | C84: 11 Investigating an issue | D84: Re-open a finished run | E84: After a run has finished: !guardian-chat message="Check the most suspicious entity again and say whether your verdict changes." Then resume the run with !setPlaybook name=GuardianInvestigateIssue, without !DeleteContext this time. (The reply names GuardianAgentLoop; either playbook resumes a re-opened run, with its own transcript and scope.) | F84: The reply says the loop was re-opened. The agent works on your request and concludes again; the trace continues from the earlier turns. | G84: Yes | I84: Not run
A85: I8 | B85: 3 With model | C85: 11 Investigating an issue | D85: Stray re-entry stops | E85: Run !setPlaybook name=GuardianInvestigateIssue on a finished issue without !DeleteContext key=Guardian first. | F85: The run stops at once with "loop already ... ignoring stray re-entry". This is expected; run !DeleteContext key=Guardian first. | I85: Not run
A86: I9 | B86: 3 With model | C86: 11 Investigating an issue | D86: Deny a proposed action | E86: If the agent proposes an action (for example closing the issue or tagging an endpoint), it is held as in section 5. Deny it with !guardian-deny approval_id=<ID> reason="test". | F86: The run carries on without the action, and the deny reason appears in its reasoning. | I86: Not run
A87: I10 | B87: 3 With model | C87: 11 Investigating an issue | D87: Investigation costs | E87: !guardian-cost | F87: The investigations' costs. If the cost is $0 with a warning, the model has no row in guardian_pricing (L7): record it. | I87: Not run
A88: G1 | B88: 3 With model | C88: 12 Conclusion-quality gate | D88: Evidence for verdicts | E88: For each run with a Benign or Malicious verdict above 70, open !GuardianLayoutToolLedger. | F88: At least one successful tool that adds evidence beyond the alert itself: an enrichment or lookup such as findIndicators or an IP, domain or endpoint check. These do not count: getIncidents, getEntries, SearchIncidentsV2, GuardianMemory, GuardianCaseNote, GuardianKBSearch, GuardianSkillRead, GuardianAskAnalyst. | I88: Not run
A89: G2 | B89: 3 With model | C89: 12 Conclusion-quality gate | D89: Corrective turn and downgrade | E89: If a run had no such evidence. | F89: One corrective turn (gate action nudged). If evidence still lacks, the verdict is recorded as Suspicious, confidence 65 or lower, with a "Guardian calibration" note (gate action downgraded). | I89: Not run
A90: G3 | B90: 3 With model | C90: 12 Conclusion-quality gate | D90: Case note and memory | E90: Each GuardianInvestigateIssue run. | F90: A case note and a memory entry were written. If either is missing, the conclusion says "the run ended without: ...". | I90: Not run
A91: C1 | B91: 3 With model | C91: 13 Drafting a playbook | D91: Draft a playbook | E91: On an issue whose run has finished: !guardian-chat message="Draft a Cortex platform playbook that enriches the IP addresses in an issue and adds a summary note. Draft only; do not import it." Then resume the run as in I7: !setPlaybook name=GuardianInvestigateIssue, without !DeleteContext. | F91: The trace shows GuardianSkillRead with build_cortex_playbook. The answer is a reviewable draft (YAML) marked as a draft. | G91: Yes | I91: Not run
A92: C2 | B92: 3 With model | C92: 13 Drafting a playbook | D92: Nothing imported | E92: Check the ledger. | F92: No playbook was imported or attached. If the agent proposed importPlaybook or setPlaybook, it was held for approval: deny it. | I92: Not run
A93: R1 | B93: 3 With model | C93: 14 Memory from the runs | D93: Search case memory | E93: !GuardianMemory op=search query="<an entity from an investigated issue>" | F93: The case memory that run stored. The War Room entry gives only the count; read the rows with !getContext key=Guardian.Memory.results. | I93: Not run
A94: R2 | B94: 3 With model | C94: 14 Memory from the runs | D94: Related issue reads memory | E94: Investigate an issue related to an earlier one (same host, user or IP address), as in I1. | F94: Its trace shows the earlier case memory being read in the first turns. | G94: Yes | I94: Not run
A95: U1 | B95: 3 With model | C95: 15 Upkeep after the runs | D95: Expiry and consolidation | E95: At least 60 minutes after A9: !GuardianHousekeeping, then !GuardianWidgetApprovalsQueue | F95: A9's approval is marked expired and no longer pending. N1's memory row (one-hour ttl) is removed. The runs' audit rows are consolidated into guardian_audit. | I95: Not run
A96: U2 | B96: 3 With model | C96: 15 Upkeep after the runs | D96: Case capture with runs | E96: Needs custom issue fields: N/A if P10 found them REJECTED or DROPPED. Close an investigated issue the normal way, then !GuardianCaseCapture | F96: A memory row for the closed issue with its verdict. Check it with R1's search. It finds closed issues by their Guardian verdict field, so it needs I3 to have found the fields written: if not, it captures nothing (record N/A). | H96: Yes | I96: Not run
A97: U3 | B97: 3 With model | C97: 15 Upkeep after the runs | D97: Evaluation harvest with runs | E97: Needs custom issue fields: N/A if P10 found them REJECTED or DROPPED. !GuardianEvalHarvest, then !getList listName=guardian_eval_cases_runtime | F97: An evaluation case made from U2's closed issue, with Guardian's verdict as the expected one. Same condition as U2; simulated issues (X1) are never harvested. | H97: Yes | I97: Not run
A98: U4 | B98: 3 With model | C98: 15 Upkeep after the runs | D98: Widgets with run data | E98: The five widget commands from O5 | F98: The tables now show the runs: costs, tool calls, loop health and events. Known gap: loop health counts only open Guardian Agent Run issues, so on a tenant where runs happen on ordinary issues it shows zeros; record it. | I98: Not run
A99: U5 | B99: 3 With model | C99: 15 Upkeep after the runs | D99: Queue triage by hand | E99: Queue triage by hand, the GuardianIntakeSweep Job's work: on the workbench issue, !DeleteContext key=Guardian, then !setPlaybook name=GuardianAgentLoop. | F99: A read-only triage of the open queue. It takes longer than one investigation. | G99: Yes | H99: Yes | I99: Not run
A100: F1 | B100: 3 With model | C100: 16 Finishing | D100: No approvals pending | E100: !GuardianWidgetApprovalsQueue | F100: No approval left pending. Deny any leftovers. | I100: Not run
A101: F2 | B101: 3 With model | C101: 16 Finishing | D101: Kill switch decision | E101: Decide the kill switch: off if Guardian stays in use, on if it should stay idle until the next session. | F101: !GuardianKillSwitchCheck shows your choice. | I101: Not run
A102: F3 | B102: 3 With model | C102: 16 Finishing | D102: Remove temporary credential | E102: If you used a temporary certificate or secret for the test, remove it from the app registration (Certificates & secrets) and give the production instance its own credential. | F102: The test credential is removed. | I102: Not run
A103: F4 | B103: 3 With model | C103: 16 Finishing | D103: Upkeep owner and schedule | E103: Agree who runs the section 8 upkeep by hand, and how often, while Guardian is in use. | F103: A named owner and schedule. | I103: Not run
A104: C1 | B104: 3 With model | C104: 17 Cortex-native investigation | D104: Route an issue | E104: In an issue's War Room run !GuardianIssueRoute. Try it on a posture finding (a CSPM, CIEM, CVE or attack-path issue) and on a threat detection if the tenant has one. | F104: Guardian.Route shows the family (misconfiguration, identity, vulnerability, code_risk, attack_path, kubernetes_cis or detection), the skill for it, the evidence plan and the assessment mode (posture or verdict). Record the family you expected against the one you got; a wrong or "unknown" family means the guardian_issue_routes list needs a row for that scanner. | I104: Not run
A105: C2 | B105: 3 With model | C105: 17 Cortex-native investigation | D105: Gather the evidence packet | E105: Run !GuardianIssueEvidence on the same issue. | F105: Guardian.Evidence.rendered holds one section per step: issue_fields, issue_status, recommendations, asset:<id>, the case, prior_rules and memory. Record every section listed under "Not available on this tenant or failed" with its error. Three calls are unverified on a real tenant and must be checked here: core-get-issues issue_id=<id> (does it return this issue?), core-get-issues rule_id=<id> status=Resolved (does it return earlier resolved issues, with their resolution?) and core-get-cloud-original-alerts alert_ids=<id> (detections only: does it take the issue id?). The call count and failures are in the readable output. No compute units are used. | I105: Not run
A106: C3 | B106: 3 With model | C106: 17 Cortex-native investigation | D106: A posture run | E106: Run GuardianInvestigateIssue on a posture issue (clear context first: !DeleteContext key=Guardian). | F106: The first entries show the route and "Evidence packet: pinned (n calls, n failed)". The model does not re-fetch what the packet holds. It checks that the condition still holds (asset details), then writes a case note in the posture report format. The conclusion ends with the posture block: assessment (Confirmed, Not reproducible or Accepted risk candidate), priority P1 to P4, exposure, owner, fix. It must not end with a Malicious/Suspicious/Benign verdict. | G106: Yes | I106: Not run
A107: C4 | B107: 3 With model | C107: 17 Cortex-native investigation | D107: Guardian did not use XSOAR commands | E107: Open the tool ledger (!GuardianLayoutToolLedger) after C3. | F107: No call to getIncidents, getEntries, SearchIncidentsV2, findIndicators or setIncident. Calls are Cortex commands (core-get-issues with page_size and output_keys, core-get-asset-details, core-get-case-extra-data) and Guardian tools. Record any call that failed on a wrong argument. | I107: Not run
A108: C5 | B108: 3 With model | C108: 17 Cortex-native investigation | D108: A detection run with XQL | E108: Run GuardianInvestigateIssue on a threat detection (domain Security), if the tenant has one. | F108: The model gathers the identity's surrounding activity (GuardianXQL identity_activity, or its own xdr-xql-generic-query), IP prevalence and user risk. The conclusion ends with a verdict block, and the end of the run shows "XQL: n queries, x compute units, y left today". Record the cost: it is the first real measurement for this tenant. | G108: Yes | I108: Not run
A109: C6 | B109: 3 With model | C109: 17 Cortex-native investigation | D109: Ready-made queries | E109: Run !GuardianXQL template=list, then !GuardianXQL template=identity_activity identity=<a user or role name seen in the cloud audit log> hours=6. | F109: The list shows four templates. The query returns rows with query_cost and remaining_quota. A value with a quote or pipe is refused with a message. A window longer than the template's usual maximum runs and adds a note. | I109: Not run
A110: C7 | B110: 3 With model | C110: 17 Cortex-native investigation | D110: Unused permissions template | E110: Run !GuardianXQL template=identity_unused_permissions identity=<a role or compute name>. | F110: Returns the identity's permissions with last-access information, or the platform's field error. This template's field name (source_cloud_resource_name) comes from the documentation and is unverified: record the exact error text if it fails. | G110: Yes | H110: Yes | I110: Not run
A111: C8 | B111: 3 With model | C111: 17 Cortex-native investigation | D111: A health issue | E111: Run GuardianInvestigateIssue on a Health-domain issue, if any exist. | F111: No model session. One short note says why. The playbook ends. | H111: Yes | I111: Not run
A112: C9 | B112: 3 With model | C112: 17 Cortex-native investigation | D112: The outcome is remembered | E112: After C3, run !GuardianMemory op=search query=run:<issue id>. | F112: One row, key run:<issue id>, naming the family, rule id, asset ids, the assessment and priority, and the summary. No Job was needed. Run C3 on a second issue of the same rule: its Gather evidence step lists the first row under "memory". | I112: Not run
A113: C10 | B113: 3 With model | C113: 17 Cortex-native investigation | D113: Rule digest | E113: Set the playbook input mode to digest and run it on an issue of a rule that has many open issues; then run it on a second issue of the same rule. | F113: The first run's evidence packet has a rule_digest section (the open issues of the rule grouped by asset) and the model writes one ranked report for the rule. The second issue gets the note "a digest for its rule was already written today" and no model session. | G113: Yes | H113: Yes | I113: Not run
A114: C11 | B114: 3 With model | C114: 17 Cortex-native investigation | D114: What Guardian is missing | E114: Run !guardian-tools. | F114: A section "On this tenant but not allowlisted" lists the installed commands Guardian may not use, per brand, with read/write counts. Record whether the counts look right for your tenant. | I114: Not run
A115: T1 | B115: 3 With model | C115: 18 Deterministic triage | D115: Rate a posture issue | E115: On a fresh issue run !DeleteContext key=Guardian, then !setPlaybook name=GuardianTriageIssue. Wait for it to finish (a few minutes). Then run !getContext key=Guardian.Triage and !guardian-cost. | F115: Guardian.Triage shows status "structured", a type from the guardian_triage_types list (for a posture finding: misconfiguration, vulnerability, code_risk, excessive_privilege, attack_path or other), a severity, a confidence from 0 to 100, escalate true or false, a summary and a branch. The sub-playbook named after the type ran. The triage session took at most 6 turns. The issue now has the phase "Guardian triage: <type>"; its status, type and description are unchanged. A case note was added. Nothing is waiting for approval. The run cost is a few cents. | G115: Yes | I115: Not run
A116: T2 | B116: 3 With model | C116: 18 Deterministic triage | D116: Dry run writes only a note | E116: On another fresh issue run !DeleteContext key=Guardian, then !setPlaybook name=GuardianTriageIssue with the playbook input apply_changes set to false. Read the issue afterwards. | F116: The case note says what would have changed. The issue's severity and phase are unchanged. Guardian.Triage is still filled in. | G116: Yes | H116: Yes | I116: Not run
A117: T3 | B117: 3 With model | C117: 18 Deterministic triage | D117: Type lookups run, or are skipped quietly | E117: Open the playbook run of T1 and read its tasks. Run !getContext key=Guardian.Evidence. | F117: The sub-playbook ran its lookups first. A lookup whose input is empty is skipped and is not shown as a failure. The results were added to the evidence packet. A posture issue has no event time, so its XQL looks back 72 hours instead of being anchored to a time. A detection issue's XQL is anchored to the detection time. | I117: Not run
A118: T4 | B118: 3 With model | C118: 18 Deterministic triage | D118: Only a clean result may change severity | E118: Read Guardian.Triage.status on every run of this section. If a run shows "repaired" or "fallback", check the issue's severity afterwards. | F118: Severity is changed only when status is "structured". A repaired or fallback result writes the phase at most and never changes severity. Record any run that is not structured, with the reason in Guardian.Triage. | I118: Not run
A119: T5 | B119: 3 With model | C119: 18 Deterministic triage | D119: Escalate means compromise only | E119: Triage an issue that is a configuration or hardening finding, with no sign of misuse (for example a storage account without a customer-managed key). | F119: Guardian.Triage.escalate is false. A finding that is only a risk, or an attempt that was blocked or failed with no sign it worked, does not escalate on its own. | G119: Yes | I119: Not run
A120: T6 | B120: 3 With model | C120: 18 Deterministic triage | D120: A triaged issue is not written again | E120: Run !DeleteContext key=Guardian and !setPlaybook name=GuardianTriageIssue again on the issue from T1. | F120: The model session and the sub-playbook run again and add a case note. GuardianTriageApply reports that it skipped: the phase already starts with "Guardian triage:". Severity and phase are not written a second time. Guardian cannot clear a phase on Cortex Cloud (core-update-issue ignores an empty value), so an issue triaged once is never written again. An issue with an owner, or one that is resolved, is skipped the same way. | G120: Yes | I120: Not run
A121: T7 | B121: 3 With model | C121: 18 Deterministic triage | D121: Case note length and resource ids | E121: Open the case note of each run in this section. | F121: Each note is under 4000 characters and was accepted without a rejection in the War Room. A cloud resource is written with its full id and is not shortened with "...". | I121: Not run
A122: T8 | B122: 3 With model | C122: 18 Deterministic triage | D122: Severity can be lowered | E122: Only when you have an issue that Guardian is likely to rate below its platform severity, for example a hardening gap with no exposure. Triage it. | F122: Severity is lowered only when the result is structured, confidence is 80 or more and escalate is false. The case note shows the before and after values and why. If no issue gets a lower rating, mark this test Skipped. | G122: Yes | H122: Yes | I122: Not run

Sheet Guide
A1: Overview
A2: Plan | B2: Testing a new Guardian deployment on a Cortex platform tenant
A3: What this plan is | B3: A manual test plan for the first session after Guardian content is installed on a new tenant. Everything here is done by hand in the console. No script or API calls are needed.
A4: Tenant profile | B4: This plan is written for a Cortex platform tenant where Jobs cannot be created or run and layouts cannot be customised or attached (for example, Cortex Cloud). Such a tenant has no Guardian tab, no buttons and no scheduled runs. Every one of those features has a text command that does the same work, and this plan uses those commands. A tenant that does have Jobs and layouts runs this whole plan and then the extra checks on the Jobs and layouts tab.
A5: Three parts
A6: Part | B6: What it covers | C6: Needs a model | D6: Billed
A7: 1. Without a model | B7: The installed content, the lists, the safeguards, approvals, kill switch, memory and skills, and the upkeep that Jobs run on other tenants | C7: No | D7: No
A8: 2. Connect the model | B8: The provider instance, its credential, and sizing the model | C8: Yes | D8: A few small calls
A9: 3. With the model | B9: Investigations, the conclusion gate, playbook drafting, and upkeep with real run data | C9: Yes | D9: Yes
A10: Where to start | B10: Part 1 can run before the model provider account exists. Finish it first: a failure in Part 1 is an install or content problem, and it is easier to find before a model is involved.
A11: Before you start | B11: Before you start, read the install guide (docs/cortex-platform/README.md); the model setup page (docs/MODEL_SETUP.md) is needed from Part 2.
A13: How to run this plan
A14: Where to type | B14: Where to type. Type commands in an issue's War Room. Pick one quiet, low-severity issue as your workbench issue for the stand-alone commands. Use separate issues for the investigations (section 11).
A15: One thing at a time | B15: One thing at a time. Run one command, wait for its result, then run the next. Never run two Guardian investigations at the same time. Do not type in an issue while its investigation is running, except to answer the agent.
A16: Billed steps | B16: Billed steps are marked (billed): they call the model and cost money. There are none in Part 1. !guardian-cost shows the running total at any time.
A17: Before every re-run | B17: Before every re-run of an investigation on the same issue, run !DeleteContext key=Guardian first.
A18: Recording | B18: Recording. Each test has an ID. Set its Status on the Tests tab (Pass, Fail, Blocked, Skipped or N/A) and put the evidence in Evidence: a screenshot name, or the War Room entry. A result that differs from the expected one is a finding: capture it anyway and write down what happened.
A19: Time | B19: Time. Part 1 takes about an hour. Parts 2 and 3 take most of half a day, mostly waiting for investigations, which take a few minutes each.
A21: What this profile can and cannot test
A22: Feature | B22: On this tenant | C22: How this plan covers it
A23: Installed content and control lists | B23: Yes | C23: Sections 1 and 2
A24: Safeguards, approvals, kill switch | B24: Yes, with commands instead of buttons | C24: Sections 4, 5, 6
A25: Memory, skills, knowledge base | B25: Yes | C25: Section 7, then section 15 with run data
A26: Upkeep that Jobs run elsewhere (housekeeping, case capture, evaluation harvest) | B26: No Jobs: run each by hand | C26: Section 8, then section 15
A27: Model provider (Foundry, Vertex, Cohere) | B27: Yes | C27: Section 10
A28: Sizing the model (the model-adaptation Job) | B28: A model in the model catalogue: its documented limits, saved by the first task of a run; no Job needed. Other models: no Job, run by hand. | C28: L9, M14, M7
A29: Investigating one issue | B29: Yes, started by hand | C29: Section 11
A30: Conclusion-quality gate | B30: Yes | C30: Section 12
A31: Playbook drafting (content engineering) | B31: Yes | C31: Section 13
A32: Scheduled queue triage (GuardianIntakeSweep Job) | B32: No Job: optional run by hand | C32: U5
A33: Guardian tab and its buttons on an issue | B33: No | C33: The !GuardianLayout* and !guardian-* commands
... A37: Guardian Performance dashboard | B37: Only if the tenant can import dashboards | C37: Optional, X3; the !GuardianWidget* commands stand in for it
A39: Section notes
A40: Section 0 Before the session | B40: For Part 1: rows B1 to B4. For Part 2 (prepare these while Part 1 runs): rows B5 to B7.
A41: Part 1: without a model | B41: Nothing in this part calls a model. Do not create the model provider instance yet: P8 checks the starting point without one.
A42: Section 2 Control lists | B42: These lists set what the agent may do. Read them and change nothing. Use !getList listName=<name> for each.
A43: Section 4 Safeguards | B43: Every action the agent takes passes through GuardianToolBridge. These tests call it by hand, in the workbench issue's War Room.
A44: Section 5 Human approval | B44: GuardianContainmentSimulate is the pack's safe stand-in for "isolate endpoint": it changes nothing and only writes a note. It passes through the same gate as real containment. Work in the workbench issue's War Room, and put the approval id that the hold step prints in place of <ID>.
A45: Section 5 Human approval (note) | B45: Credential-tier actions need confirm=CONFIRM (exact, case-sensitive) on !guardian-approve. Pending approvals expire after 60 minutes, but only when Housekeeping runs (U1).
A46: Section 6 Kill switch | B46: Change the switch only with !guardian-killswitch. Never use setList: the list is protected.
A47: Section 8 Upkeep without Jobs | B47: On a tenant with Jobs, six Jobs run Guardian's upkeep on a schedule. Here someone runs them by hand: at the end of each test session, and regularly once Guardian is in use.
A48: Section 8 Upkeep without Jobs (note) | B48: Each Job runs one playbook. The four upkeep playbooks run one script and then close the issue they run on, because a Job opens a new issue for every run. So there are two ways to run one by hand: - The script in any War Room. This is the simpler way for routine use, and nothing is closed. - The playbook on a spare issue with !setPlaybook name=<playbook>. It does exactly what a Job run does, and closes that issue at the end.
A49: End of Part 1 | B49: End of Part 1. Part 1 passes when sections 1 to 8 pass. Nothing has called a model and !guardian-cost is still zero. Fix any failure here before Part 2: see the Troubleshooting tab.
A50: Section 10 Model provider | B50: Enable exactly one Guardian provider instance at a time. Guardian sends every model call to whichever enabled instance answers guardian-llm-chat. After the instance works, M14 saves the documented limits of a model in the model catalogue and M15 sets the model size. For such a model the probe (M7) is optional.
A51: Section 10 Model provider: Certificate error cases (optional) | B51: Certificate error cases (optional). Use a second Foundry instance and press Test without enabling it. Restore or delete it afterwards.
... A58: Section 18 Deterministic triage | B58: Use a fresh issue for each run: high severity, domain Posture, no owner, empty phase. Leave the approval mode unset (manual) and approve nothing. Run them one after another. Triage rates an issue with a short model session, checks the answer against fixed values, and then fixed rules set the severity and phase and choose a sub-playbook by type. The model cannot write the issue; only GuardianTriageApply can, and only within its guards.

Sheet Jobs by hand
A1: Jobs by hand
A3: On a tenant with Jobs, six Jobs run Guardian's upkeep on a schedule.
A4: Here someone runs them by hand: at the end of each test session, and regularly once Guardian is in use.
A5: Each Job runs one playbook.
A6: The four upkeep playbooks run one script and then close the issue they run on, because a Job opens a new issue for every run.
A7: So there are two ways to run one by hand:
A8: - The script in any War Room. This is the simpler way for routine use, and nothing is closed.
A9: - The playbook on a spare issue with !setPlaybook name=<playbook>. It does exactly what a Job run does, and closes that issue at the end.
A11: Job | B11: Playbook | C11: By hand | D11: Needs a model | E11: How often
A12: GuardianHousekeeping | B12: GuardianHousekeeping | C12: !GuardianHousekeeping | D12: No | E12: Hourly on other tenants; here at least daily, and at the end of each session
A13: GuardianCaseCapture | B13: GuardianCaseCapture | C13: !GuardianCaseCapture | D13: No | E13: After closing issues that Guardian investigated (it covers the last 30 hours)
A14: GuardianEvalHarvest | B14: GuardianEvalHarvest | C14: !GuardianEvalHarvest | D14: No | E14: Daily (it covers the last 48 hours)
A15: GuardianEvalScore | B15: GuardianEvalScore | C15: !GuardianEval action=score | D15: No | E15: Only when evaluation runs exist. Evaluation runs open issues that must start a playbook by themselves, which this tenant does not do, so this Job has little to do here.
A16: GuardianModelAdaptation | B16: GuardianModelAdaptation | C16: !guardian-probe-model, then !GuardianModelProfileUpdate | D16: Yes (billed) | E16: Not needed for a model with a documented profile (M14). Otherwise after any change of model or deployment (M7).
A17: GuardianIntakeSweep | B17: GuardianAgentLoop | C17: !setPlaybook name=GuardianAgentLoop on an issue | D17: Yes (billed) | E17: Only if the customer wants queue triage (U5)
A19: Without custom issue fields | B19: GuardianCaseCapture, GuardianEvalHarvest and GuardianEvalScore find issues by the Guardian verdict field. On a tenant where P10 found custom issue fields REJECTED or DROPPED they find nothing: skip them.

Sheet Troubleshooting
A1: Symptom | B1: Likely cause
A2: !guardian-model, housekeeping or case capture fails, or the run summary stays empty | B2: No working Core REST API instance (P4)
A3: A list is missing (audit, memory, kill switch) | B3: !GuardianBootstrap was not run (P5)
A4: getList returns {"id": ..., "version": -1 ... | B4: The list was uploaded with its file wrapper; upload it again (docs/cortex-platform/MANUAL_UPLOAD.md)
A5: "playbook is not adopted" | B5: Adopt the playbooks (P3)
A6: Everything is denied | B6: The kill switch is on (!GuardianKillSwitchCheck)
A7: Test fails and mentions cryptography or the Docker image | B7: The tenant has not pulled demisto/crypto, the image Guardian Foundry runs on
A8: "Entra ID did not accept the certificate assertion" (AADSTS700027) | B8: The public certificate is not uploaded to the app registration, the thumbprint is for another certificate, or the Tenant or Client ID is wrong
A9: Entra error that the application was not found | B9: Wrong Client ID, or the app is in a different tenant from the Tenant ID
A10: HTTP 401 or 403 from Foundry | B10: No role on the resource (wait five minutes after adding one), or no custom subdomain on the resource
A11: HTTP 404 | B11: Wrong deployment name, or the project endpoint was used instead of the resource endpoint
A12: HTTP 429 | B12: The deployment's tokens-per-minute quota is too low
... A19: The probe reports a quota reached at N tokens | B19: The deployment's tokens-per-minute quota stopped the search, not its context window (B7). A closed frontier model or a model with a published cloud cap keeps its documented limit; otherwise the largest request that answered is used.

Sheet Jobs and layouts
A1: Tenant with Jobs and layouts
A3: Intro | B3: Run the whole plan, then these checks as well.
A4: Jobs | B4: Jobs: create the six Jobs (docs/cortex-platform/README.md, "Create the Jobs"). Check that GuardianHousekeeping runs hourly and that GuardianModelAdaptation writes guardian_model_profile. Enable GuardianIntakeSweep (queue triage every 6 hours) only when the customer wants scheduled triage.
A5: Issue layout | B5: Issue layout: where GuardianAgentRunLayout is attached, the Guardian tab shows the run summary, recommended actions, trace and tool ledger. Its buttons (Approve, Deny, Reply to agent, Compact transcript, Pause all runs, Resume all runs) do the same as the commands in sections 5 to 11.
A6: SOC Agent page | B6: SOC Agent page: the guardian:primary indicator page and its buttons (Refresh Tools, Agent Readiness, Validate Tools, Apply Policy, Export Config, New Investigation). Apply Policy narrows the tool allowlist; run !guardian-tools before and after it.

Sheet Changes
A1: Date | B1: ID | C1: Change | D1: In a copy made earlier
A2: 2026-10-10 | B2: L9 | C2: New: the model catalogue list | D2: Optional; run it before Part 2.
A3: 2026-10-10 | B3: L2 | C3: More to note: model_tier, max_input_tokens, incident_fields_enabled and the cap comment | D3: No re-run needed.
A4: 2026-10-10 | B4: B5 | C4: A client secret is listed next to the certificate | D4: No action.
A5: 2026-10-10 | B5: M1 | C5: Reworded: the Model dropdown, and a client secret as an alternative to the certificate | D5: No re-run needed.
A6: 2026-10-10 | B6: M2 | C6: N/A with a client secret | D6: Mark it N/A if you used a client secret.
A7: 2026-10-10 | B7: M4 | C7: Expected changed: before any profile is saved, a model in the catalogue shows its documented budget | D7: Re-run now (needs GuardianModelCommand from 2026-10-10 on the tenant).
A8: 2026-10-10 | B8: M14 | C8: New: documented profile saved | D8: Run now, after M4.
A9: 2026-10-10 | B9: M15 | C9: New: model size | D9: Run now, after M14.
A10: 2026-10-10 | B10: M7 | C10: Optional for a model with a documented profile; the budget does not change | D10: Run when you reach it.
A11: 2026-10-10 | B11: M13 | C11: Also repeats M14 and M15 | D11: No action.
A12: 2026-10-10 | B12: I1 | C12: Expected adds the Resolve model profile entry | D12: Run when you reach it.
... A28: 2026-10-13 | B28: R1, T8, U4 | C28: R1 says where the search rows are (context, not the War Room entry). T8 has now been seen on a live tenant. U4 notes that loop health shows zeros when runs happen on ordinary issues. | D28: No re-run needed.
